acslib/__init__.py
acslib/base/__init__.py
acslib/base/acs.py
acslib/base/config.py
acslib/base/connection.py
acslib/base/search.py
acslib/base/status.py
acslib/ccure/__init__.py
acslib/ccure/actions.py
acslib/ccure/base.py
acslib/ccure/config.py
acslib/ccure/connection.py
acslib/ccure/crud.py
acslib/ccure/data_models.py
acslib/ccure/endpoints.py
acslib/ccure/filters.py
acslib/ccure/types.py
acslib/ccure/tests/__init__.py
acslib/ccure/tests/conftest.py
acslib/ccure/tests/test_base.py
acslib/ccure/tests/test_config.py
acslib/ccure/tests/test_connection.py
acslib/ccure/tests/test_search.py
acslib-0.1.16.dist-info/LICENSE
acslib-0.1.16.dist-info/WHEEL
acslib-0.1.16.dist-info/METADATA
acslib-0.1.16.dist-info/RECORD
