Metadata-Version: 2.1
Name: acslib
Version: 0.1.16
Summary: A library for interacting with Access Control Systems like Genetec or Ccure9k
Author-email: Jeremy Gibson <jmgibso3@ncsu.edu>, Luc Sanchez <lgsanche@ncsu.edu>, Ryan Semmler <rsemmle@ncsu.edu>
Requires-Python: >=3.10
Requires-Dist: pydantic>=2.5.3, <3.0.0
Requires-Dist: sat-utils>=1.1.12, <2.0.0
Requires-Dist: pytest>=6.2.5, <7.0.0 ; extra == "dev"
Requires-Dist: pytest-cov>=4.0.0, <5.0.0 ; extra == "dev"
Requires-Dist: pytest-mock>=3.10.0, <4.0.0 ; extra == "dev"
Requires-Dist: coverage[toml]>=6.2 ; extra == "dev"
Requires-Dist: black>=23.3.0, <24.0.0 ; extra == "dev"
Requires-Dist: ruff==0.1.1 ; extra == "dev"
Requires-Dist: mkdocs-material>=9.4.6, <10.0.0 ; extra == "dev"
Requires-Dist: pymdown-extensions>=10.3.1, <11.0.0 ; extra == "dev"
Requires-Dist: mkdocs-include-markdown-plugin>=6.0.3, <7.0.0 ; extra == "dev"
Requires-Dist: mkdocstrings>=0.23.0, <1.0.0 ; extra == "dev"
Requires-Dist: mkdocstrings-python>=1.7.3, <2.0.0 ; extra == "dev"
Requires-Dist: Pygments>=2.10.0, <3.0.0 ; extra == "dev"
Requires-Dist: bandit>=1.7.4, <2.0.0 ; extra == "dev"
Requires-Dist: bandit[toml]>=1.7.4, <2.0.0 ; extra == "dev"
Requires-Dist: pre-commit>=2.16.0, <3.0.0 ; extra == "dev"
Requires-Dist: isort>=5.10.1, <6.0.0 ; extra == "dev"
Requires-Dist: pyupgrade>=2.29.1, <3.0.0 ; extra == "dev"
Requires-Dist: flit>=3.8.0, <4.0.0 ; extra == "dev"
Requires-Dist: Faker>=20.0.0, <21.0.0 ; extra == "dev"
Project-URL: Homepage, https://github.ncsu.edu/SAT/acslib
Provides-Extra: dev
